Metadata-Version: 2.1
Name: EdgeGPT-fork
Version: 1.0.3
Summary: Reverse engineered Edge Chat API
Home-page: https://github.com/xingty/EdgeGPT
Author: Antonio Cheong,Bigbyto
Author-email: acheong@student.dalat.org,bigbyto@gmail.com
License: The Unlicense
Project-URL: Bug Report, https://github.com/xingty/EdgeGPT/issues/new
Classifier: License :: OSI Approved :: The Unlicense (Unlicense)
Classifier: Intended Audience :: Developers
Classifier: Topic :: Software Development :: Libraries :: Python Modules
Classifier: Programming Language :: Python :: 3.8
Classifier: Programming Language :: Python :: 3.9
Classifier: Programming Language :: Python :: 3.10
Classifier: Programming Language :: Python :: 3.11
License-File: LICENSE
Requires-Dist: httpx[socks] >=0.24.0
Requires-Dist: aiohttp
Requires-Dist: websockets
Requires-Dist: rich
Requires-Dist: certifi
Requires-Dist: prompt-toolkit
Requires-Dist: requests
Requires-Dist: BingImageCreator-fork >=0.7.6
Requires-Dist: curl-cffi
